FastStatic/FastStatic.py
FastStatic/__init__.py
FastStatic-0.0.1.dist-info/LICENCE.txt
FastStatic-0.0.1.dist-info/METADATA
FastStatic-0.0.1.dist-info/WHEEL
FastStatic-0.0.1.dist-info/top_level.txt
FastStatic-0.0.1.dist-info/RECORD
