Metadata-Version: 2.1
Name: FastStatic
Version: 0.0.1
Summary: Satatic Functions
Author: Tareq Abeda
Author-email: <TareqAbeda@outlook.com>
Keywords: python,video,stream,video stream,camera stream,sockets
Classifier: Development Status :: 1 - Planning
Classifier: Intended Audience :: Developers
Classifier: Programming Language :: Python :: 3
Classifier: Operating System :: Unix
Classifier: Operating System :: MacOS :: MacOS X
Classifier: Operating System :: Microsoft :: Windows
License-File: LICENCE.txt
Requires-Dist: pandas
Requires-Dist: datetime
Requires-Dist: logging
